MIDRC_MELODY/__init__.py
MIDRC_MELODY/__main__.py
MIDRC_MELODY/melody.py
MIDRC_MELODY/melody_gui.py
MIDRC_MELODY/common/__init__.py
MIDRC_MELODY/common/data_loading.py
MIDRC_MELODY/common/data_preprocessing.py
MIDRC_MELODY/common/edit_config.py
MIDRC_MELODY/common/eod_aaod_metrics.py
MIDRC_MELODY/common/generate_eod_aaod_spiders.py
MIDRC_MELODY/common/generate_qwk_spiders.py
MIDRC_MELODY/common/matplotlib_spider.py
MIDRC_MELODY/common/plot_tools.py
MIDRC_MELODY/common/plotly_spider.py
MIDRC_MELODY/common/qwk_metrics.py
MIDRC_MELODY/common/table_tools.py
MIDRC_MELODY/gui/__init__.py
MIDRC_MELODY/gui/config_editor.py
MIDRC_MELODY/gui/data_loading.py
MIDRC_MELODY/gui/main_controller.py
MIDRC_MELODY/gui/main_window.py
MIDRC_MELODY/gui/matplotlib_spider_widget.py
MIDRC_MELODY/gui/metrics_model.py
MIDRC_MELODY/gui/plotly_spider_widget.py
MIDRC_MELODY/gui/qchart_spider_widget.py
MIDRC_MELODY/gui/tqdm_handler.py
MIDRC_MELODY/gui/shared/__init__.py
MIDRC_MELODY/gui/shared/react/__init__.py
MIDRC_MELODY/gui/shared/react/copyabletableview.py
MIDRC_MELODY/gui/shared/react/grabbablewidget.py
MIDRC_MELODY/resources/MIDRC.ico
midrc_melody-0.3.3.dist-info/licenses/LICENSE
midrc_melody-0.3.3.dist-info/METADATA
midrc_melody-0.3.3.dist-info/WHEEL
midrc_melody-0.3.3.dist-info/entry_points.txt
midrc_melody-0.3.3.dist-info/top_level.txt
midrc_melody-0.3.3.dist-info/RECORD
