Metadata-Version: 2.4
Name: MIDRC_MELODY
Version: 0.3.3
Summary: MELODY: Model EvaLuation across subgroups for cOnsistent Decision accuracY
Author-email: Robert Tomek <rtomek@uchicago.edu>
License-Expression: Apache-2.0
Project-URL: Homepage, https://github.com/MIDRC/MIDRC_MELODY
Project-URL: Issues, https://github.com/MIDRC/MIDRC_MELODY/issues
Keywords: machine-learning,model-evaluation,fairness,subgroup-analysis
License-File: LICENSE
Requires-Dist: pandas
Requires-Dist: matplotlib
Requires-Dist: numpy
Requires-Dist: scikit-learn
Requires-Dist: PyYAML
Requires-Dist: joblib
Requires-Dist: tqdm
Requires-Dist: tabulate
Requires-Dist: tqdm-joblib
Requires-Dist: mplcursors
Requires-Dist: windows-curses; sys_platform == "win32"
Requires-Dist: PySide6>=6.8.0
Dynamic: license-file
